{
  "season": 4,
  "season_name": "2026 - Regular Season",
  "last_updated": "2026-06-02T22:22:06.206080+00:00",
  "great_lakes_west": {
    "first_half": [],
    "second_half": [
      {
        "team_id": 86,
        "name": "Grand Forks Spitfires",
        "abbr": "GF",
        "division": "NWL Softball",
        "logo": "https://assets.northwoodsleague.com/scorebook/images/teams/86-GrandForksSpitfires-1762910017.png",
        "W": 0,
        "L": 0,
        "T": 0,
        "PCT": ".000",
        "GB": "-",
        "STREAK": "-",
        "LAST10": "-",
        "first_half_clinched": 0,
        "second_half_clinched": 0
      },
      {
        "team_id": 1,
        "name": "La Crosse Steam",
        "abbr": "LC",
        "division": "NWL Softball",
        "logo": "https://assets.northwoodsleague.com/scorebook/images/teams/1STEAM_PRIMARY_500.png",
        "W": 0,
        "L": 0,
        "T": 0,
        "PCT": ".000",
        "GB": 0,
        "STREAK": "-",
        "LAST10": "-",
        "first_half_clinched": 0,
        "second_half_clinched": 0
      },
      {
        "team_id": 4,
        "name": "Madison Night Mares",
        "abbr": "MD",
        "division": "NWL Softball",
        "logo": "https://assets.northwoodsleague.com/scorebook/images/teams/4Mare-A-Moon-500.png",
        "W": 0,
        "L": 0,
        "T": 0,
        "PCT": ".000",
        "GB": 0,
        "STREAK": "-",
        "LAST10": "-",
        "first_half_clinched": 0,
        "second_half_clinched": 0
      },
      {
        "team_id": 2,
        "name": "Mankato Habaneros",
        "abbr": "MK",
        "division": "NWL Softball",
        "logo": "https://assets.northwoodsleague.com/scorebook/images/teams/2Habaneros_PepperFlameAlt_500.png",
        "W": 0,
        "L": 0,
        "T": 0,
        "PCT": ".000",
        "GB": 0,
        "STREAK": "-",
        "LAST10": "-",
        "first_half_clinched": 0,
        "second_half_clinched": 0
      },
      {
        "team_id": 3,
        "name": "Minot Honeybees",
        "abbr": "MT",
        "division": "NWL Softball",
        "logo": "https://assets.northwoodsleague.com/scorebook/images/teams/3Honeybees_Primary_500.png",
        "W": 0,
        "L": 0,
        "T": 0,
        "PCT": ".000",
        "GB": 0,
        "STREAK": "-",
        "LAST10": "-",
        "first_half_clinched": 0,
        "second_half_clinched": 0
      },
      {
        "team_id": 5,
        "name": "Wausau Ignite",
        "abbr": "WS",
        "division": "NWL Softball",
        "logo": "https://assets.northwoodsleague.com/scorebook/images/teams/5Wausau-Ignite-500.png",
        "W": 0,
        "L": 0,
        "T": 0,
        "PCT": ".000",
        "GB": 0,
        "STREAK": "-",
        "LAST10": "-",
        "first_half_clinched": 0,
        "second_half_clinched": 0
      }
    ],
    "full": [
      {
        "team_id": 86,
        "name": "Grand Forks Spitfires",
        "abbr": "GF",
        "division": "NWL Softball",
        "logo": "https://assets.northwoodsleague.com/scorebook/images/teams/86-GrandForksSpitfires-1762910017.png",
        "W": 0,
        "L": 0,
        "T": 0,
        "PCT": ".000",
        "GB": "-",
        "STREAK": "-",
        "LAST10": "",
        "first_half_clinched": 0,
        "second_half_clinched": 0
      },
      {
        "team_id": 1,
        "name": "La Crosse Steam",
        "abbr": "LC",
        "division": "NWL Softball",
        "logo": "https://assets.northwoodsleague.com/scorebook/images/teams/1STEAM_PRIMARY_500.png",
        "W": 0,
        "L": 0,
        "T": 0,
        "PCT": ".000",
        "GB": 0,
        "STREAK": "-",
        "LAST10": "",
        "first_half_clinched": 0,
        "second_half_clinched": 0
      },
      {
        "team_id": 4,
        "name": "Madison Night Mares",
        "abbr": "MD",
        "division": "NWL Softball",
        "logo": "https://assets.northwoodsleague.com/scorebook/images/teams/4Mare-A-Moon-500.png",
        "W": 0,
        "L": 0,
        "T": 0,
        "PCT": ".000",
        "GB": 0,
        "STREAK": "-",
        "LAST10": "",
        "first_half_clinched": 0,
        "second_half_clinched": 0
      },
      {
        "team_id": 2,
        "name": "Mankato Habaneros",
        "abbr": "MK",
        "division": "NWL Softball",
        "logo": "https://assets.northwoodsleague.com/scorebook/images/teams/2Habaneros_PepperFlameAlt_500.png",
        "W": 0,
        "L": 0,
        "T": 0,
        "PCT": ".000",
        "GB": 0,
        "STREAK": "-",
        "LAST10": "",
        "first_half_clinched": 0,
        "second_half_clinched": 0
      },
      {
        "team_id": 3,
        "name": "Minot Honeybees",
        "abbr": "MT",
        "division": "NWL Softball",
        "logo": "https://assets.northwoodsleague.com/scorebook/images/teams/3Honeybees_Primary_500.png",
        "W": 0,
        "L": 0,
        "T": 0,
        "PCT": ".000",
        "GB": 0,
        "STREAK": "-",
        "LAST10": "",
        "first_half_clinched": 0,
        "second_half_clinched": 0
      },
      {
        "team_id": 5,
        "name": "Wausau Ignite",
        "abbr": "WS",
        "division": "NWL Softball",
        "logo": "https://assets.northwoodsleague.com/scorebook/images/teams/5Wausau-Ignite-500.png",
        "W": 0,
        "L": 0,
        "T": 0,
        "PCT": ".000",
        "GB": 0,
        "STREAK": "-",
        "LAST10": "",
        "first_half_clinched": 0,
        "second_half_clinched": 0
      }
    ]
  },
  "great_lakes_east": {
    "first_half": [],
    "second_half": [],
    "full": []
  }
}